zyndai_agent/__init__.py
zyndai_agent/agent.py
zyndai_agent/communication.py
zyndai_agent/identity.py
zyndai_agent/message.py
zyndai_agent/payment.py
zyndai_agent/search.py
zyndai_agent/utils.py
zyndai_agent/webhook_communication.py
zyndai_agent-0.2.1.dist-info/METADATA
zyndai_agent-0.2.1.dist-info/WHEEL
zyndai_agent-0.2.1.dist-info/top_level.txt
zyndai_agent-0.2.1.dist-info/RECORD
