Metadata-Version: 2.4
Name: zyndai-agent
Version: 0.2.1
Summary: A Langchain and Autogen wrapper that enables agents to communicate and establish identity on the Zynd AI Network. This SDK provides three core capabilities: Identity Management, Agent Discovery & Search, and HTTP Webhook or MQTT-based Communication.
Author-email: Swapnil Shinde <swapnilshinde9382@gmail.com>
Requires-Python: >=3.12
Requires-Dist: base58>=2.1.1
Requires-Dist: cryptography>=46.0.3
Requires-Dist: eth-account>=0.13.7
Requires-Dist: flask>=3.0.0
Requires-Dist: langchain>=1.1.0
Requires-Dist: paho-mqtt>=2.1.0
Requires-Dist: requests>=2.31.0
Requires-Dist: x402==1.0.0
